soar_sdk/__init__.py
soar_sdk/abstract.py
soar_sdk/action_results.py
soar_sdk/actions_manager.py
soar_sdk/app.py
soar_sdk/app_cli_runner.py
soar_sdk/app_client.py
soar_sdk/asset.py
soar_sdk/asset_state.py
soar_sdk/async_utils.py
soar_sdk/colors.py
soar_sdk/compat.py
soar_sdk/crypto.py
soar_sdk/es_client.py
soar_sdk/exceptions.py
soar_sdk/field_utils.py
soar_sdk/input_spec.py
soar_sdk/logging.py
soar_sdk/params.py
soar_sdk/paths.py
soar_sdk/py.typed
soar_sdk/types.py
soar_sdk/apis/__init__.py
soar_sdk/apis/artifact.py
soar_sdk/apis/container.py
soar_sdk/apis/utils.py
soar_sdk/apis/vault.py
soar_sdk/apis/es/findings.py
soar_sdk/app_templates/basic_app/.gitignore
soar_sdk/app_templates/basic_app/.pre-commit-config.yaml
soar_sdk/app_templates/basic_app/logo.svg
soar_sdk/app_templates/basic_app/logo_dark.svg
soar_sdk/app_templates/basic_app/uv.lock
soar_sdk/app_templates/basic_app/src/__init__.py
soar_sdk/auth/__init__.py
soar_sdk/auth/client.py
soar_sdk/auth/factories.py
soar_sdk/auth/flows.py
soar_sdk/auth/httpx_auth.py
soar_sdk/auth/models.py
soar_sdk/cli/__init__.py
soar_sdk/cli/cli.py
soar_sdk/cli/path_utils.py
soar_sdk/cli/utils.py
soar_sdk/cli/init/__init__.py
soar_sdk/cli/init/cli.py
soar_sdk/cli/manifests/__init__.py
soar_sdk/cli/manifests/cli.py
soar_sdk/cli/manifests/deserializers.py
soar_sdk/cli/manifests/processors.py
soar_sdk/cli/manifests/serializers.py
soar_sdk/cli/package/cli.py
soar_sdk/cli/package/utils.py
soar_sdk/cli/test/__init__.py
soar_sdk/cli/test/cli.py
soar_sdk/code_renderers/__init__.py
soar_sdk/code_renderers/action_renderer.py
soar_sdk/code_renderers/app_renderer.py
soar_sdk/code_renderers/asset_renderer.py
soar_sdk/code_renderers/renderer.py
soar_sdk/code_renderers/toml_renderer.py
soar_sdk/code_renderers/templates/pyproject.toml.jinja
soar_sdk/decorators/__init__.py
soar_sdk/decorators/action.py
soar_sdk/decorators/make_request.py
soar_sdk/decorators/on_es_poll.py
soar_sdk/decorators/on_poll.py
soar_sdk/decorators/test_connectivity.py
splunk_soar_sdk-3.7.0.dist-info/METADATA
splunk_soar_sdk-3.7.0.dist-info/WHEEL
splunk_soar_sdk-3.7.0.dist-info/entry_points.txt
splunk_soar_sdk-3.7.0.dist-info/licenses/LICENSE
splunk_soar_sdk-3.7.0.dist-info/RECORD
