Metadata-Version: 2.4
Name: splunk-soar-sdk
Version: 3.7.0
Summary: The official framework for developing and testing Splunk SOAR Apps
Project-URL: Homepage, https://github.com/phantomcyber/splunk-soar-sdk
Project-URL: Documentation, https://github.com/phantomcyber/splunk-soar-sdk
Project-URL: Repository, https://github.com/phantomcyber/splunk-soar-sdk
Author-email: Jacob Davis <jacobd@splunk.com>, Tapish Jain <tapishj@splunk.com>, Janusz Kamieński <jkamienski@splunk.com>, Michael Nordby <mnordby@splunk.com>, Scott Odle <sodle@splunk.com>, Michał Posłuszny <mposluszny@splunk.com>, Ian Rokas <grokas@splunk.com>
License-Expression: Apache-2.0
License-File: LICENSE
Keywords: app,cisco,connector,phantom,sdk,soar,splunk
Classifier: Development Status :: 5 - Production/Stable
Classifier: Intended Audience :: Developers
Classifier: License :: OSI Approved :: Apache Software License
Classifier: Natural Language :: English
Classifier: Programming Language :: Python :: 3
Classifier: Topic :: Software Development :: Libraries :: Python Modules
Classifier: Typing :: Typed
Requires-Python: <3.15,>=3.13
Requires-Dist: authlib>=1.3.0
Requires-Dist: beautifulsoup4>=4.10.0
Requires-Dist: bleach>=6.2.0
Requires-Dist: build>=1.3.0
Requires-Dist: click<8.2.0,>=8.0.0
Requires-Dist: distro>=1.8.0
Requires-Dist: hatchling>=1.28.0
Requires-Dist: httpx-retries>=0.4.5
Requires-Dist: httpx>=0.28.1
Requires-Dist: humanize>=4.12.2
Requires-Dist: jinja2>=3.1.0
Requires-Dist: packaging>=25.0
Requires-Dist: pydantic<3,>=2
Requires-Dist: pyjwt[crypto]>=2.8.0
Requires-Dist: requests<3
Requires-Dist: setuptools>=80.9.0
Requires-Dist: toml<1,>=0.10.2
Requires-Dist: tqdm>=4.67.1
Requires-Dist: typer<1,>=0.12.5
Provides-Extra: email
Requires-Dist: python-magic>=0.4.27; extra == 'email'
